{"name":"rtrace","className":"ModuleScript","filePaths":["src/init.luau","default.project.json"],"children":[{"name":"Assert","className":"ModuleScript","filePaths":["src/Assert.luau"]},{"name":"Enum","className":"Folder","children":[{"name":"Level","className":"ModuleScript","filePaths":["src/Enum/Level.luau"]}]},{"name":"Formatter","className":"ModuleScript","filePaths":["src/Formatter.luau"]},{"name":"Scope","className":"ModuleScript","filePaths":["src/Scope.luau"]},{"name":"Subscriber","className":"ModuleScript","filePaths":["src/Subscriber.luau"]},{"name":"Writer","className":"ModuleScript","filePaths":["src/Writer.luau"]},{"name":"Logger","className":"ModuleScript","filePaths":["src/Logger.luau"]},{"name":"Rtrace","className":"ModuleScript","filePaths":["src/Rtrace.luau"]}]}